MEMORY/MEMORY.v
module MEMORY #(parameter WIDTH = 8)
	(input [31:0] Din,
	input [7:0] Addr,
	input rw,
	input Valid,
	input reset,
	input clk,
	output reg [31:0] Dout);

	integer pos;

	reg [31:0] Mem [0:(8'b1<<WIDTH)-1];

	always @(posedge clk, posedge reset) begin

		if(reset) begin

			for(pos = 0; pos < (8'b1<<WIDTH); pos = pos+1)
				Mem[pos] <= 32'h0;
			
			Dout <= 32'h0;

		end else begin

			if(Valid) begin
				if(rw) begin
					Mem[Addr] <= Din;
					Dout <= {32{1'bz}};
				end
				else
					Dout <= Mem[Addr];
			end
			else
					Dout <= {32{1'bz}};
		end

	end

endmodule

MEMORY/tb_MEMORY.v
module testbench_MEMORY;
	parameter WIDTH = 8;
	reg [31:0] Din;
	reg [7:0] Addr;
	reg rw;
	reg Valid;
	reg reset;
	reg clk;
	wire [31:0] Dout;

	MEMORY DUT (Din, Addr, rw, Valid, reset, clk, Dout);

	initial begin

		$dumpvars(0, testbench_MEMORY);
		$dumpfile("my.vcd");

		clk = 0;
		forever
			#5 clk = ~clk;

	end

	initial begin 

		reset = 1;
		Din = 32'h5;
		Addr = 8'h0;
		#5
		display;

		reset = 0;
		Valid = 1;
		rw = 1;
		Din = 32'h5;
		Addr = 8'h0;
		#5
		display;

		rw = 1;
		Din = 32'h5;
		Addr = 8'h0;
		#5
		display;

		rw = 0;
		Din = 32'h5;
		Addr = 8'h0;
		#5
		display;

		rw = 1;
		Din = 32'h5;
		Addr = 8'h0;
		#5
		display;

		Valid = 0;
		rw = 1;
		Din = 32'h5;
		Addr = 8'h0;
		#5
		display;

		Valid = 1;
		rw = 1;
		Din = 32'hF00;
		Addr = 8'h2C;
		#5
		display;

		rw = 0;
		Din = 32'hF00;
		Addr = 8'h2C;
		#5
		display;

		rw = 1;
		Din = 32'hF00;
		Addr = 8'h2C;
		#13
		display;

		rw = 0;
		Din = 32'hF00;
		Addr = 8'h2C;
		#5
		display;



		#270
		$finish;
		end
	
	task display;
		$display("reset = %0h, clk = %0h, valid = %0h, rw = %0h, Din = %0h, Addr = %0h, Dout = %0h", reset, clk, Valid, rw, Din, Addr, Dout);
	endtask

endmodule

MEMORY/dump.vcd
$date
	Wed Jul  6 19:05:03 2022
$end
$version
	Icarus Verilog
$end
$timescale
	1s
$end
$scope module testbench_MEMORY $end
$var wire 32 ! Dout [31:0] $end
$var reg 8 " Addr [7:0] $end
$var reg 32 # Din [31:0] $end
$var reg 1 $ Valid $end
$var reg 1 % clk $end
$var reg 1 & reset $end
$var reg 1 ' rw $end
$scope module DUT $end
$var wire 8 ( Addr [7:0] $end
$var wire 32 ) Din [31:0] $end
$var wire 1 $ Valid $end
$var wire 1 % clk $end
$var wire 1 & reset $end
$var wire 1 ' rw $end
$var reg 32 * Dout [31:0] $end
$var integer 32 + pos [31:0] $end
$upscope $end
$scope task display $end
$upscope $end
$upscope $end
$enddefinitions $end
#0
$dumpvars
b100000000 +
b0 *
b101 )
b0 (
x'
1&
0%
x$
b101 #
b0 "
b0 !
$end
#5
bz !
bz *
1'
1$
0&
1%
#10
0%
#15
b101 !
b101 *
0'
1%
#20
1'
0%
#25
bz !
bz *
0$
1%
#30
b101100 "
b101100 (
b111100000000 #
b111100000000 )
1$
0%
#35
b0 !
b0 *
0'
1%
#40
1'
0%
#45
bz !
bz *
1%
#50
0%
#53
0'
#55
b111100000000 !
b111100000000 *
1%
