DIV_FREQ/DIV_FREQ.v
module DIV_FREQ(
	input [31:0] Din,
	input conf_div,
	input enable,
	input reset,
	input clk,
	output reg clk_out
);

	reg [31:0] t = 32'h1;
	reg [31:0] count = 32'h0;
	reg [31:0] pos_count = 32'h0;
	reg [31:0] neg_count = 32'h0;

	always @(posedge clk, posedge reset) begin

		if(reset) begin

			t <= 32'h1;
			clk_out <= clk;
			pos_count <= 32'h0;

		end

		else begin

			
			if(!enable) begin

				clk_out <= 0;

			  if(pos_count == t-1) 
				  pos_count <= 0;
			  else pos_count <= pos_count + 1;

				if(!conf_div) begin
					
					if(t == 1)
						clk_out <= clk;

					if(t == (t / 2 * 2)) begin

					//clk_out <= t * clk
					count <= count + 32'h1;
					if(count >= (t - 1))
						count <= 32'h0;
					clk_out <= (count < t / 2) ? 1'b1 : 1'b0;

					end

			end

				else
					t <= Din;
		end


			else begin

			  if(pos_count == Din-1) 
				  pos_count <= 0;
			  else pos_count <= pos_count + 1;

			  if(Din == 1)
				  clk_out <= clk;

					if(Din == (Din / 2 * 2)) begin

					//clk_out <= Din * clk;
					count <= count + 32'h1;
					if(count >= (Din - 1))
						count <= 32'h0;
					clk_out <= (count < Din / 2) ? 1'b1 : 1'b0;

					end

			end

		end

	end
			
	always @(negedge clk, posedge reset) begin

		if(reset) begin

			t <= 32'h1;
			clk_out <= clk;
			neg_count <= 32'h0;

		end

		else begin

			  if(Din == 1)
				  clk_out <= clk;

			  if(t == 1)
				  clk_out <= clk;

			if (!enable && neg_count == t - 1)
				neg_count <= 0;
			else if(!enable) neg_count <= neg_count + 1;

			if (enable && neg_count == Din - 1)
				neg_count <= 0;
			else if(enable) neg_count <= neg_count + 1;

			end
	end

	always @(pos_count, neg_count) begin

		if(!reset) begin

			if(!enable)
				if(t != t / 2 * 2)
					clk_out <= ((pos_count > (t >> 1)) | (neg_count > (t >> 1)));

			if(enable)
				if(Din != Din / 2 * 2)
					clk_out <= ((pos_count > (Din >> 1)) | (neg_count > (Din >> 1))); 

		end

	end




	//assign clk_out = ((t != t / 2 * 2)) ? ((!enable) ? ((pos_count > (t >> 1)) | (neg_count > (t >> 1))) : ((pos_count > (Din >> 1)) | (neg_count > (Din >> 1)))) : clk_out;

endmodule

DIV_FREQ/tb_DIV_FREQ.v
module tb_DIV_FREQ;

	reg [31:0] Din;
	reg conf_div;
	reg ctrl_tr_dat;
	reg reset;
	reg clk;
	wire clk_out;

	DIV_FREQ DUT (Din, conf_div, ctrl_tr_dat, reset, clk, clk_out);

	initial begin

		$dumpvars(0,tb_DIV_FREQ);
    	$dumpfile("my.vcd");

		clk = 0;
		forever
			#5 clk = ~clk;

	end

	initial begin

		reset = 1;
		#5
		display;

		reset = 0;
		Din = 32'h3;
		ctrl_tr_dat = 1;
		#5
		display;
		#5
		display;
		#5
		display;
		#5
		display;
		#5
		display;
		#5
		display;
		#5
		display;
		#5
		display;
		#5
		display;
		#5
		display;

		reset = 1;
		ctrl_tr_dat = 0;
		#5
		display;

		reset = 0;
		Din = 32'h2;
		conf_div = 1;
		#5
		display;
		#5

		conf_div = 0;
		Din = 32'h3;
		display;
		#5
		display;
		#5
		display;
		#5
		display;
		#5
		display;
		#5
		display;
		#5
		display;


		#5
		display;
		#5
		display;
		#5
		display;
		#5
		display;
		#5
		display;

		#300
		$finish;
	end



	task display;
		$display("r = %0h, clk = %0h, clk_out = %0h, Din = %0h, conf_div = %0h, ctrl_tr_dat = %0h, ", reset, clk, clk_out, Din, conf_div, ctrl_tr_dat);
	endtask

endmodule

DIV_FREQ/dump.vcd
$date
	Wed Jul 13 00:07:35 2022
$end
$version
	Icarus Verilog
$end
$timescale
	1s
$end
$scope module tb_DIV_FREQ $end
$var wire 1 ! clk_out $end
$var reg 32 " Din [31:0] $end
$var reg 1 # clk $end
$var reg 1 $ conf_div $end
$var reg 1 % ctrl_tr_dat $end
$var reg 1 & reset $end
$scope module DUT $end
$var wire 32 ' Din [31:0] $end
$var wire 1 # clk $end
$var wire 1 $ conf_div $end
$var wire 1 % enable $end
$var wire 1 & reset $end
$var reg 1 ! clk_out $end
$var reg 32 ( count [31:0] $end
$var reg 32 ) neg_count [31:0] $end
$var reg 32 * pos_count [31:0] $end
$var reg 32 + t [31:0] $end
$upscope $end
$scope task display $end
$upscope $end
$upscope $end
$enddefinitions $end
#0
$dumpvars
b1 +
b0 *
b0 )
b0 (
bx '
1&
x%
x$
0#
bx "
0!
$end
#5
b1 *
1%
b11 "
b11 '
0&
1#
#10
b1 )
0#
#15
1!
b10 *
1#
#20
b10 )
1!
0#
#25
b0 *
1#
#30
b0 )
0!
0#
#35
b1 *
1#
#40
b1 )
0#
#45
1!
b10 *
1#
#50
b10 )
1!
0#
#55
b0 )
b0 *
0%
1&
1#
#60
0!
1$
b10 "
b10 '
0&
0#
#65
b10 +
1#
#70
b1 )
b11 "
b11 '
0$
0#
#75
1!
b1 (
b1 *
1#
#80
b0 )
0#
#85
b0 (
b0 *
0!
1#
#90
b1 )
0#
#95
1!
b1 (
b1 *
1#
#100
b0 )
0#
#105
b0 (
b0 *
0!
1#
#110
b1 )
0#
#115
1!
b1 (
b1 *
1#
#120
b0 )
0#
#125
b0 (
b0 *
0!
1#
#130
b1 )
0#
#135
1!
b1 (
b1 *
1#
#140
b0 )
0#
#145
b0 (
b0 *
0!
1#
#150
b1 )
0#
#155
1!
b1 (
b1 *
1#
#160
b0 )
0#
#165
b0 (
b0 *
0!
1#
#170
b1 )
0#
#175
1!
b1 (
b1 *
1#
#180
b0 )
0#
#185
b0 (
b0 *
0!
1#
#190
b1 )
0#
#195
1!
b1 (
b1 *
1#
#200
b0 )
0#
#205
b0 (
b0 *
0!
1#
#210
b1 )
0#
#215
1!
b1 (
b1 *
1#
#220
b0 )
0#
#225
b0 (
b0 *
0!
1#
#230
b1 )
0#
#235
1!
b1 (
b1 *
1#
#240
b0 )
0#
#245
b0 (
b0 *
0!
1#
#250
b1 )
0#
#255
1!
b1 (
b1 *
1#
#260
b0 )
0#
#265
b0 (
b0 *
0!
1#
#270
b1 )
0#
#275
1!
b1 (
b1 *
1#
#280
b0 )
0#
#285
b0 (
b0 *
0!
1#
#290
b1 )
0#
#295
1!
b1 (
b1 *
1#
#300
b0 )
0#
#305
b0 (
b0 *
0!
1#
#310
b1 )
0#
#315
1!
b1 (
b1 *
1#
#320
b0 )
0#
#325
b0 (
b0 *
0!
1#
#330
b1 )
0#
#335
1!
b1 (
b1 *
1#
#340
b0 )
0#
#345
b0 (
b0 *
0!
1#
#350
b1 )
0#
#355
1!
b1 (
b1 *
1#
#360
b0 )
0#
#365
b0 (
b0 *
0!
1#
#370
b1 )
0#
#375
1!
b1 (
b1 *
1#
#380
b0 )
0#
#385
b0 (
b0 *
0!
1#
#390
b1 )
0#
#395
1!
b1 (
b1 *
1#
#400
b0 )
0#
#405
b0 (
b0 *
0!
1#
#410
b1 )
0#
#415
1!
b1 (
b1 *
1#
#420
b0 )
0#
#425
b0 (
b0 *
0!
1#
