M_ALU/M_ALU.v
module M_ALU(

	input [7:0] A,
	input [7:0] B,
	input [3:0] SEL_TMP,
	output reg [7:0] ALU_OUT_TMP,
	output reg [3:0] FLAG_TMP

);

reg zf = 1'b0;
reg cf = 1'b0;
reg of = 1'b0;
reg uf = 1'b0;
reg [7:0] neg;

always @(*) begin

zf = 1'b0;
cf = 1'b0;
of = 1'b0;
uf = 1'b0;

	case(SEL_TMP)

		4'h0:

			{cf, ALU_OUT_TMP} = A + B;
		
		4'h1: begin

			if(A < B)
				uf = 1;

			neg = ~B + 1;

			ALU_OUT_TMP = A + neg;

			end

		4'h2: begin

			if(A > 8'hF && B > 8'hF)
				of = 1;

			ALU_OUT_TMP = A * B;

		end

		4'h3: begin

			if(A < B)
				uf = 1;

			ALU_OUT_TMP = A / B;

		end

		4'h4: begin

			{cf, ALU_OUT_TMP} = A << B;

		end

		4'h5: begin

			{ALU_OUT_TMP, cf} = A >> B;

		end

		4'h6:

			ALU_OUT_TMP = A & B;

		4'h7:

			ALU_OUT_TMP = A | B;

		4'h8:

			ALU_OUT_TMP = A ^ B;

		4'h9:

			ALU_OUT_TMP = A ~^ B;

		4'hA:

			ALU_OUT_TMP = A ~& B;

		4'hB:

			ALU_OUT_TMP = A ~| B;

		default: begin

			ALU_OUT_TMP = 8'h00;
			FLAG_TMP = 4'h0;

		end

	endcase

	if(ALU_OUT_TMP == 0 && SEL_TMP <= 4'hB)

		zf = 1;

	FLAG_TMP = {uf, of, cf, zf};


end


endmodule

M_ALU/tb_M_ALU.v
module testbench_M_ALU;
  
  reg [7:0] A;
  reg [7:0] B;
  
  reg [3:0] SEL_TMP;
  
  
  wire [7:0] ALU_OUT_TMP;
  wire [3:0] FLAG_TMP;
  
  M_ALU DUT(.ALU_OUT_TMP(ALU_OUT_TMP),
             .FLAG_TMP(FLAG_TMP),
             .A(A),
             .B(B),
             .SEL_TMP(SEL_TMP)
            );
  
  
  initial begin
     // Dump waves
    $dumpfile("dump.vcd");
    $dumpvars(1);
    
    
    // sum w/o carry
    
    #1
    
    SEL_TMP = 4'h0;
    A= 8'b0010_1011;
    B= 8'b0000_0100;
    
    #1
    
    display;
    
    // sum w/ carry
    
    SEL_TMP = 4'h0;
    A= 8'b1010_1011;
    B= 8'b1000_0100;
    
    #1
    
    display;
    
    
    // sub w/o underflow
    
    SEL_TMP = 4'h1;
    A= 8'b0010_1011;
    B= 8'b0000_0100;
    
    #1
    
    display;
    
    // sub w/ underflow
    
    SEL_TMP = 4'h1;
    B = 8'b0010_1011;
    A = 8'b0000_0100;
    
    #1
    
    display;

    // multiplication w/o overflow
    
    SEL_TMP = 4'h2;
    A = 8'b0010_1011;
    B = 8'b0000_0100;
    
    #1
    
    display;
    
    // multiplication w/ overflow
    
    SEL_TMP = 4'h2;
    A = 8'b1010_1011;
    B = 8'b1000_0100;
    
    #1
    
    display;
    
    // division w/o underflow
    
    SEL_TMP = 4'h3;
    A = 8'b0010_1011;
    B = 8'b0000_0100;
    
    #1
    
    display;
    
    // division w/ underflow
    
    SEL_TMP = 4'h3;
    B = 8'b0010_1011;
    A = 8'b0000_0100;
    
    #1
    
    display;
    
    // left shifting w/o ZeroFlag
    
    SEL_TMP = 4'h4;
    A= 8'b0010_1011;
    B= 8'b0000_0100;
    
    #1
    
    display;
    
    // left shifting w/ ZeroFlag
    
    SEL_TMP = 4'h4;
    A= 8'b0010_1011;
    B= 8'b0000_0011;
    
    #1
    
    display;
    
    // right shifting w/o ZeroFlag
    
    SEL_TMP = 4'h5;
    A= 8'b0010_1011;
    B= 8'b0000_0100;
    
    #1
    
    display;
    
    // right shifting w/ ZeroFlag
    
    SEL_TMP = 4'h5;
    A= 8'b0010_1011;
    B= 8'b1000_0100;
    
    #1
    
    display;
    
    // AND
    
    SEL_TMP = 4'h6;
    A= 8'b0010_1011;
    B= 8'b0000_0110;
    
    #1
    
    display;
    
    // OR
    
    SEL_TMP = 4'h7;
    A= 8'b0010_1011;
    B= 8'b0000_0100;
    
    #1
    
    display;
    
    // XOR
    
    SEL_TMP = 4'h8;
    A= 8'b0010_1011;
    B= 8'b0000_0100;
    
    #1
    
    display;
    
    // NXOR
    
    SEL_TMP = 4'h9;
    A= 8'b0010_1011;
    B= 8'b0000_0100;
    
    #1
    
    display;
    
    // NAND
    
    SEL_TMP = 4'hA;
    A= 8'b0010_1011;
    B= 8'b0000_0100;
    
    #1
    
    display;
    
    // NOR
    
    SEL_TMP = 4'hB;
    A= 8'b0010_1011;
    B= 8'b0000_0100;
    
    #1
    
    display;
    
    
    // DEFAULT
    
    SEL_TMP = 4'hC;
    A= 8'b0010_1011;
    B= 8'b0000_0100;
    
    #1
    
    display;
   
  end
  
  task display;
    $display("A:%b, B:%b, SEL_TMP:%h, ALU_OUT_TMP:%b, FLAG_TMP:%b",
             A, B, SEL_TMP, ALU_OUT_TMP, FLAG_TMP);
  endtask
  
endmodule

M_ALU/dump.vcd
$date
	Wed Jul  6 19:03:53 2022
$end
$version
	Icarus Verilog
$end
$timescale
	1s
$end
$scope module testbench_M_ALU $end
$var wire 4 ! FLAG_TMP [3:0] $end
$var wire 8 " ALU_OUT_TMP [7:0] $end
$var reg 8 # A [7:0] $end
$var reg 8 $ B [7:0] $end
$var reg 4 % SEL_TMP [3:0] $end
$upscope $end
$enddefinitions $end
#0
$dumpvars
bx %
bx $
bx #
b0 "
b0 !
$end
#1
b101111 "
b100 $
b101011 #
b0 %
#2
b10 !
b10000100 $
b10101011 #
#3
b0 !
b100111 "
b100 $
b101011 #
b1 %
#4
b1000 !
b11011001 "
b100 #
b101011 $
#5
b0 !
b10101100 "
b100 $
b101011 #
b10 %
#6
b100 !
b101100 "
b10000100 $
b10101011 #
#7
b0 !
b1010 "
b100 $
b101011 #
b11 %
#8
b1001 !
b0 "
b100 #
b101011 $
#9
b0 !
b10110000 "
b100 $
b101011 #
b100 %
#10
b10 !
b1011000 "
b11 $
#11
b0 !
b1 "
b100 $
b101 %
#12
b1 !
b0 "
b10000100 $
#13
b0 !
b10 "
b110 $
b110 %
#14
b101111 "
b100 $
b111 %
#15
b1000 %
#16
b11010000 "
b1001 %
#17
b11111111 "
b1010 %
#18
b11010000 "
b1011 %
#19
b0 "
b1100 %
