REG_SHIFT_PLOAD/REG_SHIFT_PLOAD.v
module REG_SHIFT_PLOAD(
	input [31:0] Din,
	input p_load,
	input start_tx,
	input reset,
	input clk,
	input clk_tx,
	output reg tx_done,
	output reg tx_busy,
	output reg Dout
);

	integer pos = 0;
	reg [31:0] buffer;
	reg r_v;

	always @(posedge clk, posedge reset) begin

		if(reset) begin

			buffer <= 32'h0;
			pos <= 1'b0;
			tx_busy <= 1'b0;
			tx_done <= 1'b0;
			Dout <= 1'bz;

		end

		else begin

			if(p_load && !start_tx && clk) begin

				r_v <= 1'b1;

				for(pos = 0; pos < 32; pos = pos + 1)
					if(Din [pos] == 1'bz || Din [pos] == 1'bz)
						r_v <= 1'b0;

				if(r_v)
				buffer <= Din;

			pos <= 0;

			end


		end


	end


	always @(posedge clk_tx, posedge reset) begin

		if(reset) begin

			buffer <= 32'h0;
			pos <= 1'b0;
			tx_busy <= 1'b0;
			tx_done <= 1'b0;

		end

		else begin

			if(!p_load && r_v && pos <= 32) begin

				if(pos < 31) begin
					tx_busy <= 1'b1;
					Dout <= buffer [pos];
				end

				if(pos == 31) begin
					tx_done <= 1'b1;
				end

				if(pos == 32) begin
					tx_done <= 1'b0;
					tx_busy <= 1'b0;
					Dout <= 1'bz;
				end

				pos <= pos + 1;

			end


		end

	end

endmodule

REG_SHIFT_PLOAD/tb_REG_SHIFT_PLOAD.v
module tb_REG_SHIFT_PLOAD;

	reg [31:0] Din;
	reg p_load;
	reg start_tx;
	reg reset;
	reg clk;
	reg clk_tx;
	wire tx_done;
	wire tx_busy;
	wire Dout;

	REG_SHIFT_PLOAD DUT (Din, p_load, start_tx, reset, clk, clk_tx, tx_done, tx_busy, Dout);

	initial begin

		$dumpvars(0,tb_REG_SHIFT_PLOAD);
    	$dumpfile("my.vcd");

		clk = 0;
		forever
			#5 clk = ~clk;

	end

	initial begin

		clk_tx = 0;
		forever
			#10 clk_tx = ~clk_tx;

	end

	initial begin

		reset = 1;
		#5
		display;

		reset = 0;
		Din = 32'hF0F0FF0F;
		p_load = 1'b1;
		start_tx = 1'b0;
		#15
		display;

		p_load = 1'b0;
		start_tx = 1'b1;
		#5
		display;

		#5
		display;
		#5
		display;
		#5
		display;
		#5
		display;
		#5
		display;

		#650
		$finish;

	end
		
		task display;
		$display("r = %0h, clk = %0h, clk_tx = %0h, Din = %0h, p_load = %0h, start_tx = %0h, tx_done = %0h, tx_busy = %0h, Dout = %0h,", reset, clk, clk_tx, Din, p_load, start_tx, tx_done, tx_busy, Dout);
	endtask



endmodule

REG_SHIFT_PLOAD/dump.vcd
$date
	Tue Jul 12 17:19:11 2022
$end
$version
	Icarus Verilog
$end
$timescale
	1s
$end
$scope module tb_REG_SHIFT_PLOAD $end
$var wire 1 ! tx_done $end
$var wire 1 " tx_busy $end
$var wire 1 # Dout $end
$var reg 32 $ Din [31:0] $end
$var reg 1 % clk $end
$var reg 1 & clk_tx $end
$var reg 1 ' p_load $end
$var reg 1 ( reset $end
$var reg 1 ) start_tx $end
$scope module DUT $end
$var wire 32 * Din [31:0] $end
$var wire 1 % clk $end
$var wire 1 & clk_tx $end
$var wire 1 ' p_load $end
$var wire 1 ( reset $end
$var wire 1 ) start_tx $end
$var reg 1 # Dout $end
$var reg 32 + buffer [31:0] $end
$var reg 1 , r_v $end
$var reg 1 " tx_busy $end
$var reg 1 ! tx_done $end
$var integer 32 - pos [31:0] $end
$upscope $end
$scope task display $end
$upscope $end
$upscope $end
$enddefinitions $end
#0
$dumpvars
b0 -
x,
b0 +
bx *
x)
1(
x'
0&
0%
bx $
z#
0"
0!
$end
#5
1,
b0 -
0)
1'
b11110000111100001111111100001111 $
b11110000111100001111111100001111 *
0(
1%
#10
0%
1&
#15
b11110000111100001111111100001111 +
b0 -
1%
#20
0%
0&
1)
0'
#25
1%
#30
b1 -
1#
1"
0%
1&
#35
1%
#40
0%
0&
#45
1%
#50
b10 -
0%
1&
#55
1%
#60
0%
0&
#65
1%
#70
b11 -
0%
1&
#75
1%
#80
0%
0&
#85
1%
#90
b100 -
0%
1&
#95
1%
#100
0%
0&
#105
1%
#110
b101 -
0#
0%
1&
#115
1%
#120
0%
0&
#125
1%
#130
b110 -
0%
1&
#135
1%
#140
0%
0&
#145
1%
#150
b111 -
0%
1&
#155
1%
#160
0%
0&
#165
1%
#170
b1000 -
0%
1&
#175
1%
#180
0%
0&
#185
1%
#190
b1001 -
1#
0%
1&
#195
1%
#200
0%
0&
#205
1%
#210
b1010 -
0%
1&
#215
1%
#220
0%
0&
#225
1%
#230
b1011 -
0%
1&
#235
1%
#240
0%
0&
#245
1%
#250
b1100 -
0%
1&
#255
1%
#260
0%
0&
#265
1%
#270
b1101 -
0%
1&
#275
1%
#280
0%
0&
#285
1%
#290
b1110 -
0%
1&
#295
1%
#300
0%
0&
#305
1%
#310
b1111 -
0%
1&
#315
1%
#320
0%
0&
#325
1%
#330
b10000 -
0%
1&
#335
1%
#340
0%
0&
#345
1%
#350
b10001 -
0#
0%
1&
#355
1%
#360
0%
0&
#365
1%
#370
b10010 -
0%
1&
#375
1%
#380
0%
0&
#385
1%
#390
b10011 -
0%
1&
#395
1%
#400
0%
0&
#405
1%
#410
b10100 -
0%
1&
#415
1%
#420
0%
0&
#425
1%
#430
b10101 -
1#
0%
1&
#435
1%
#440
0%
0&
#445
1%
#450
b10110 -
0%
1&
#455
1%
#460
0%
0&
#465
1%
#470
b10111 -
0%
1&
#475
1%
#480
0%
0&
#485
1%
#490
b11000 -
0%
1&
#495
1%
#500
0%
0&
#505
1%
#510
b11001 -
0#
0%
1&
#515
1%
#520
0%
0&
#525
1%
#530
b11010 -
0%
1&
#535
1%
#540
0%
0&
#545
1%
#550
b11011 -
0%
1&
#555
1%
#560
0%
0&
#565
1%
#570
b11100 -
0%
1&
#575
1%
#580
0%
0&
#585
1%
#590
b11101 -
1#
0%
1&
#595
1%
#600
0%
0&
#605
1%
#610
b11110 -
0%
1&
#615
1%
#620
0%
0&
#625
1%
#630
b11111 -
0%
1&
#635
1%
#640
0%
0&
#645
1%
#650
b100000 -
0"
1!
0%
1&
#655
1%
#660
0%
0&
#665
1%
#670
b100001 -
z#
0!
0%
1&
