CONTROLLER/dff.v
// D flip-flop
module dff (clk, reset,
  d, q);
  input      clk;
  input      reset;
  input      d;
  output     q;

  reg        q;

  always @(posedge clk or posedge reset)
  begin
    if (reset) begin
      // Asynchronous reset when reset goes high
      q <= 1'b0;
    end else begin
      // Assign D to Q on positive clock edge
      q <= d;
    end
  end
endmodule

CONTROLLER/DEC_INPUT_KEY.v
module DEC_INPUT_KEY(
	input input_key,
	input valid_cmd,
	input reset,
	input clk,
	output active,
	output mode);

	localparam IDLE = 3'b 000;
	localparam S1 = 3'b 001;
	localparam S2 = 3'b 011;
	localparam S3 = 3'b 010;
	localparam S4 = 3'b 110;
	localparam S5 = 3'b 111;
	localparam S6 = 3'b 101;


	wire s0 , s1 , s2 ;
	wire s0v, s1v, s2v;

	assign s2v = ~s2 & s1 & ~s0 & valid_cmd & ~input_key | s2 & s1 & ~s0 & valid_cmd | s2 & s0;
	assign s1v = ~s2 & ~s1 & s0 & valid_cmd & ~input_key | ~s2 & s1 & s0 & valid_cmd & input_key | s1 & ~s0 & valid_cmd & ~input_key | s2 & s1 & s0;
	assign s0v = ~s2 & ~s1 & ~s0 & valid_cmd & input_key | ~s2 & ~s1 & s0 & valid_cmd & ~input_key | s2 & s1 & ~s0 & valid_cmd | s2 & s0;

	dff d0(clk, reset, s0v, s0);
	dff d1(clk, reset, s1v, s1);
	dff d2(clk, reset, s2v, s2);

	assign mode = s2 & ~s1 & s0;
	assign active = s2 & s0;

endmodule

CONTROLLER/tb_DEC_INPUT_KEY.v
module tb_DEC_INPUT_KEY;

	reg input_key;
	reg valid_cmd;
	reg reset;
	reg clk;
	wire active;
	wire mode;

	DEC_INPUT_KEY DUT (input_key, valid_cmd, reset, clk, active, mode);

	initial begin

                $dumpvars(0, tb_DEC_INPUT_KEY);
                $dumpfile("my.vcd");

                clk = 0;
                forever
                        #5 clk = ~clk;

        end

	
	initial begin

		reset = 1;
		valid_cmd = 0;
		input_key = 0;
		#4
		display;

		reset = 0;
		valid_cmd = 1;
		input_key = 1;
		#12
		display;

		valid_cmd = 1;
		input_key = 0;
		#12
		display;

		valid_cmd = 1;
		input_key = 1;
		#12
		display;

		valid_cmd = 1;
		input_key = 0;
		#12
		display;

		valid_cmd = 1;
		input_key = 1;
		#12
		display;

		valid_cmd = 1;
		input_key = 0;
		#12
		display;

		#300
		$finish;

	end


	task display;
		$display("reset = %0h, clk = %0h, valid = %0h, in = %0h, active = %0h, mode = %0h", reset, clk, valid_cmd, input_key, active, mode);
	endtask

endmodule

CONTROLLER/dump.vcd
$date
	Wed Jul 13 15:08:09 2022
$end
$version
	Icarus Verilog
$end
$timescale
	1s
$end
$scope module tb_DEC_INPUT_KEY $end
$var wire 1 ! mode $end
$var wire 1 " active $end
$var reg 1 # clk $end
$var reg 1 $ input_key $end
$var reg 1 % reset $end
$var reg 1 & valid_cmd $end
$scope module DUT $end
$var wire 1 " active $end
$var wire 1 # clk $end
$var wire 1 $ input_key $end
$var wire 1 ! mode $end
$var wire 1 % reset $end
$var wire 1 ' s0v $end
$var wire 1 ( s1v $end
$var wire 1 ) s2v $end
$var wire 1 & valid_cmd $end
$var wire 1 * s2 $end
$var wire 1 + s1 $end
$var wire 1 , s0 $end
$scope module d0 $end
$var wire 1 # clk $end
$var wire 1 ' d $end
$var wire 1 % reset $end
$var reg 1 , q $end
$upscope $end
$scope module d1 $end
$var wire 1 # clk $end
$var wire 1 ( d $end
$var wire 1 % reset $end
$var reg 1 + q $end
$upscope $end
$scope module d2 $end
$var wire 1 # clk $end
$var wire 1 ) d $end
$var wire 1 % reset $end
$var reg 1 * q $end
$upscope $end
$upscope $end
$scope task display $end
$upscope $end
$upscope $end
$enddefinitions $end
#0
$dumpvars
0,
0+
0*
0)
0(
0'
0&
1%
0$
0#
0"
0!
$end
#4
1'
1$
1&
0%
#5
0'
1,
1#
#10
0#
#15
1'
0,
1#
#16
0'
0$
#20
0#
#25
1#
#28
1'
1$
#30
0#
#35
0'
1,
1#
#40
1(
1'
0#
0$
#45
0'
0(
1+
1#
#50
0#
#52
1(
1$
#55
0(
0,
1#
#60
0#
#64
1)
1(
0$
#65
1'
1*
1#
#70
0#
#75
1"
1,
1#
